{"lastClose": 2.8299999237060547, "len": 114, "date": "2023-02-02", "alpha_3mo": 8.843857416954464, "beta_3mo": 1.5539227112434264, "drawup_3mo": 3.205052029631215, "sharpe_3mo": 2.018137369279655, "natr_3mo": 10.97689102194292, "sup_3mo": -0.10011777709631436, "res_3mo": 0.07184925205646561, "bullPattern_3mo": ["3OUTSIDE"], "bearPattern_3mo": [], "rsi_3mo": 84.32432557824242, "adx_3mo": 74.35298686524801, "drawdown_3mo": -0.5819875949777793, "stratHoldSharpe_3mo": 2.1188995008850684, "stratHoldAlpha_3mo": 254.96950539092092, "stratHoldDrawdown_3mo": -0.5270625164578668, "Industry": "Movies/Entertainment", "Sector": "Consumer Discretionary", "Market Cap": 1487668083, "Name": "AMC Entertainment Holdings Inc. AMC Preferred Equity Units each constituting a depositary share representing a 1/100th interest in a share of Series A Convertible Participating Preferred Stock", "IPO Year": 2022.0, "alpha%_3mo": 1.0, "beta%_3mo": 0.8123715072051053, "drawup%_3mo": 1.0, "sharpe%_3mo": 0.3510183872837875, "natr%_3mo": 0.9991054551399585, "drawdown%_3mo": 5.13548445589356e-06, "stratHoldSharpe%_3mo": 0.6147517486977662, "stratHoldAlpha%_3mo": 0.9999997550519318, "stratHoldDrawdown%_3mo": 5.245519108685412e-06}