{"lastClose": 2.2200000286102295, "len": 128, "date": "2023-02-23", "alpha_3mo": 294.3276288211693, "beta_3mo": 1.2033228357278156, "drawup_3mo": 3.6953940398541647, "sharpe_3mo": 2.0325997580738173, "natr_3mo": 14.027097183606788, "sup_3mo": -0.2282282224230523, "res_3mo": 0.14264261216546895, "bullPattern_3mo": ["HIKKAKE"], "bearPattern_3mo": [], "rsi_3mo": 33.14918029483015, "adx_3mo": 32.05787488402082, "drawdown_3mo": -0.40964913463988806, "stratHoldSharpe_3mo": 2.178082865228774, "stratHoldAlpha_3mo": 255.14503741259432, "stratHoldDrawdown_3mo": -0.3686842211758993, "Name": "AMC Entertainment Holdings Inc. AMC Preferred Equity Units each constituting a depositary share representing a 1/100th interest in a share of Series A Convertible Participating Preferred Stock", "Industry": "Movies/Entertainment", "Market Cap": 1161425082, "Sector": "Consumer Discretionary", "IPO Year": 2022.0, "alpha%_3mo": 1.0, "beta%_3mo": 0.6575928876802973, "drawup%_3mo": 1.0, "sharpe%_3mo": 0.725847954586778, "natr%_3mo": 0.9999820732925633, "drawdown%_3mo": 0.0008419827556384952, "stratHoldSharpe%_3mo": 0.7901834242504392, "stratHoldAlpha%_3mo": 0.9999999999993129, "stratHoldDrawdown%_3mo": 0.0009670967316438066}