{"lastClose": 17.84000015258789, "len": 250, "date": "2023-02-14", "alpha_3mo": 7.938285255375025, "beta_3mo": 0.8930013152692458, "drawup_3mo": 1.8203343292677543, "sharpe_3mo": 2.2415752624636847, "natr_3mo": 5.3756615374843095, "sup_3mo": -0.20427878309162534, "res_3mo": 0.141498467528067, "bullPattern_3mo": ["DOJI", "HIGHWAVE", "LONGLEGGEDDOJI", "RICKSHAWMAN", "SPINNINGTOP"], "bearPattern_3mo": ["DOJISTAR", "HIKKAKE"], "rsi_3mo": 65.47486303183136, "adx_3mo": 53.4290330257852, "drawdown_3mo": -0.4743777519368805, "stratHoldSharpe_3mo": 2.263437322001952, "stratHoldAlpha_3mo": 254.402172302713, "stratHoldDrawdown_3mo": -0.43856219574871946, "Sector": "Health Care", "Market Cap": 416558394, "Country": "China", "Industry": "Medical Specialities", "Name": "Meihua International Medical Technologies Co. Ltd. Ordinary Shares", "IPO Year": 2022.0, "alpha%_3mo": 1.0, "beta%_3mo": 0.45612673486672495, "drawup%_3mo": 1.0, "sharpe%_3mo": 0.6601819096323668, "natr%_3mo": 0.740854327891808, "drawdown%_3mo": 3.4010734355836646e-05, "stratHoldSharpe%_3mo": 0.7491062459196911, "stratHoldAlpha%_3mo": 0.9999999958938329, "stratHoldDrawdown%_3mo": 1.879389540279996e-05}